{
  "planTable": [
    {
      "id": "pjxmQXifP",
      "createDate": "2021-3-27 19:14:20",
      "content": "位安然发起人我而去单位安然发起人我而去单位安然发起人我而去单位安然发起人我而去单位安然发起人我而去单位安然发起人我而去单位安然发起人我而去单位安然发起人我而单位安然发起人我而去单位安然发起人我而去单位安然发起人我而去单位安然发起人我而去单位安然发起人我而去单位安然发起人我而去单位安然发起人我而去单位安然发起人我而去单位安然发起人我而去单位安然发起人我而去单位安然发起人我而去单位安然发起人我而去单位安然发起人我而去单位安然发起人我而去单位安然发起人我而去单位安然发起人我而去单位安然发起人我而去单位安然发起人我而去单位安然发起人我而去单位安然发起人我而去单位安然发起人我而去单位安然发起人我而去单位安然发起人我而去单位安然发起人我而去单位安然发起人我而去单位安然发起人我而去单位安然发起人我而去单位安然发起人我而去单位安然发起人我而去单位安然发起人我而去单位安然发起人我而去单位安然发起人我而去单位安然发起人我而去单位安然发起人我而去单位安然发起人我而去单位安然发起人我而去单位安然发起人我而去",
      "updateDate": "2021-3-28 01:00:15"
    },
    {
      "id": "RMgoBoRcxS",
      "createDate": "2021-3-27 19:46:35"
    },
    {
      "id": "fC2Y8tvNWN",
      "createDate": "2021-3-27 19:46:36"
    },
    {
      "id": "o2WXrAFZA",
      "createDate": "2021-3-27 19:46:36"
    },
    {
      "id": "XFbbAOsbtX",
      "createDate": "2021-3-27 19:46:36"
    },
    {
      "id": "jd-tIFh7hh",
      "createDate": "2021-3-27 19:46:36"
    },
    {
      "id": "N7RVbd33B_",
      "createDate": "2021-3-27 19:46:36",
      "content": "-",
      "updateDate": "2021-3-27 19:47:15"
    },
    {
      "id": "lGAuy62W_P",
      "createDate": "2021-3-27 19:46:36"
    },
    {
      "id": "xlv0qQJIJ",
      "createDate": "2021-3-27 19:46:37"
    },
    {
      "id": "r3xQR_eM-",
      "createDate": "2021-3-27 19:48:28"
    },
    {
      "id": "eAfQ6TpxU",
      "createDate": "2021-3-27 19:48:29"
    }
  ]
}